<?xml version="1.0" encoding="UTF-8"?>
<UnityGameFramework>
  <ResourceBuilder>
    <Settings>
      <InternalResourceVersion>1</InternalResourceVersion>
      <Platforms>1</Platforms>
      <AssetBundleCompression>1</AssetBundleCompression>
      <CompressionHelperTypeName>UnityGameFramework.Runtime.DefaultCompressionHelper</CompressionHelperTypeName>
      <AdditionalCompressionSelected>True</AdditionalCompressionSelected>
      <ForceRebuildAssetBundleSelected>True</ForceRebuildAssetBundleSelected>
      <BuildEventHandlerTypeName>RoundHero.Editor.StarForceBuildEventHandler</BuildEventHandlerTypeName>
      <OutputDirectory>I:/NewWork/RoundHero/UnityProject/RoundHero/Outputs</OutputDirectory>
      <OutputPackageSelected>True</OutputPackageSelected>
      <OutputFullSelected>False</OutputFullSelected>
      <OutputPackedSelected>False</OutputPackedSelected>
    </Settings>
  </ResourceBuilder>
</UnityGameFramework>